parser.py
notsimilarname123456789-0.0.1.dist-info/licenses/LICENSE.txt
notsimilarname123456789-0.0.1.dist-info/METADATA
notsimilarname123456789-0.0.1.dist-info/WHEEL
notsimilarname123456789-0.0.1.dist-info/top_level.txt
notsimilarname123456789-0.0.1.dist-info/RECORD
